interferopy/__init__.py
interferopy/casatools.py
interferopy/casatools_vla_pipe.py
interferopy/cube.py
interferopy/tools.py
interferopy/data/default.param
interferopy/data/default.sex
interferopy-1.0.4.dist-info/LICENSE
interferopy-1.0.4.dist-info/METADATA
interferopy-1.0.4.dist-info/WHEEL
interferopy-1.0.4.dist-info/top_level.txt
interferopy-1.0.4.dist-info/RECORD
