Metadata-Version: 2.1
Name: interferopy
Version: 1.0.4
Summary: radio-to-mm interferometric data analysis package
Home-page: https://interferopy.readthedocs.io/en/latest/
Author: Leindert Boogard, Romain Meyer, Mladen Novak
Author-email: boogard@mpia.de, meyer@mpia.de
License: MIT License
Project-URL: Bug Tracker, https://github.com/interferopy/interferopy/issues
Classifier: Programming Language :: Python :: 3
Requires-Python: >=3.7
License-File: LICENSE
Requires-Dist: numpy>=1.20
Requires-Dist: scipy>=1.7
Requires-Dist: matplotlib>=3.4
Requires-Dist: tqdm>=4.62
Requires-Dist: astropy>=4.3
